{
  "common": {
    "name": "open-wa",
    "version": "0.3.5",
    "title": "Open-WA WhatsApp Gateway",
    "titleLang": {
      "en": "Open-WA WhatsApp Gateway",
      "de": "Open-WA WhatsApp Gateway"
    },
    "desc": {
      "en": "Send WhatsApp messages via gateway /sendText (Bearer token, group support, fixed Admin UI test button)",
      "de": "WhatsApp Nachrichten über Gateway /sendText senden (Bearer Token, Gruppensupport, korrigierter Test-Button in der Admin UI)"
    },
    "authors": [
      "radebold <radebold@users.noreply.github.com>"
    ],
    "license": "MIT",
    "platform": "Javascript/Node.js",
    "mode": "daemon",
    "type": "messaging",
    "icon": "open-wa.png",
    "enabled": true,
    "loglevel": "info",
    "connectionType": "local",
    "dataSource": "push",
    "adminUI": {
      "config": "json"
    },
    "main": "main.js",
    "blockly": true,
    "messagebox": true,
    "news": {
      "en": "0.3.5 Fixed the Admin UI test button by switching to jsonData placeholders and added backend support for the test command.",
      "de": "0.3.5 Admin-UI-Testbutton korrigiert: Platzhalter werden jetzt per jsonData aufgelöst, zusätzlich verarbeitet das Backend den Test-Befehl."
    }
  },
  "native": {
    "serverIp": "192.168.178.10",
    "serverPort": 3020,
    "token": ""
  },
  "objects": [],
  "instanceObjects": [],
  "version": "0.3.5"
}
